ofxstatement_otp-0.1.1-py3.9-nspkg.pth
ofxstatement/plugins/otp.py
ofxstatement/plugins/otp_credit_legacy.py
ofxstatement/plugins/otp_legacy.py
ofxstatement_otp-0.1.1.dist-info/METADATA
ofxstatement_otp-0.1.1.dist-info/WHEEL
ofxstatement_otp-0.1.1.dist-info/entry_points.txt
ofxstatement_otp-0.1.1.dist-info/namespace_packages.txt
ofxstatement_otp-0.1.1.dist-info/top_level.txt
ofxstatement_otp-0.1.1.dist-info/zip-safe
ofxstatement_otp-0.1.1.dist-info/RECORD
