Metadata-Version: 2.1
Name: ofxstatement-otp
Version: 0.1.1
Summary: ofxstatement plugin for the Hungarian bank OTP
Home-page: https://github.com/gyp/ofxstatement-otp
Author: Peter Gyongyosi
Author-email: gypeter@gmail.com
License: AGPLv3
Keywords: ofx,banking,statement
Platform: UNKNOWN
Classifier: Development Status :: 4 - Beta
Classifier: Programming Language :: Python :: 3
Classifier: Natural Language :: English
Classifier: Topic :: Office/Business :: Financial :: Accounting
Classifier: Topic :: Utilities
Classifier: Environment :: Console
Classifier: Operating System :: OS Independent
Classifier: License :: OSI Approved :: GNU Affero General Public License v3
Requires-Dist: ofxstatement
Requires-Dist: openpyxl
Requires-Dist: dataclasses
